MANIFEST.in
README.md
setup.py
biro/__init__.py
biro/router.py
biro.egg-info/PKG-INFO
biro.egg-info/SOURCES.txt
biro.egg-info/dependency_links.txt
biro.egg-info/top_level.txt