Metadata-Version: 1.1
Name: biro
Version: 0.0.3
Summary: bidirectional URI routing
Home-page: https://github.com/zweifisch/biro
Author: Feng Zhou
Author-email: zf.pascal@gmail.com
License: MIT
Keywords: bidirectional routing
Platform: UNKNOWN
Classifier: Development Status :: 3 - Alpha
Classifier: Environment :: Web Environment
Classifier: Operating System :: OS Independent
Classifier: Intended Audience :: Developers
Classifier: License :: OSI Approved :: MIT License
Classifier: Programming Language :: Python :: 3.3
Classifier: Topic :: Internet :: WWW/HTTP :: WSGI
